vnpy_jees-6.6.1.1.dist-info/METADATA
vnpy_jees-6.6.1.1.dist-info/WHEEL
vnpy_jees/api/vnjeestd.cp313-win_amd64.pyd
vnpy_jees/api/vnjeestd.cp313-win_amd64.lib
vnpy_jees/__init__.py
vnpy_jees/api/__init__.py
vnpy_jees/api/jees_constant.py
vnpy_jees/gateway/__init__.py
vnpy_jees/gateway/jees_gateway.py
vnpy_jees/api/thosttraderapi_se.dll
vnpy_jees-6.6.1.1.dist-info/RECORD
